pysm4/__init__.py
pysm4/sm4.py
pysm4-0.7.2.dist-info/LICENSE
pysm4-0.7.2.dist-info/METADATA
pysm4-0.7.2.dist-info/WHEEL
pysm4-0.7.2.dist-info/top_level.txt
pysm4-0.7.2.dist-info/RECORD
